oftest/__init__.py
oftest/load_data.py
oftest/utils.py
oftest-0.2.1.dist-info/AUTHORS.rst
oftest-0.2.1.dist-info/LICENSE
oftest-0.2.1.dist-info/METADATA
oftest-0.2.1.dist-info/WHEEL
oftest-0.2.1.dist-info/top_level.txt
oftest-0.2.1.dist-info/RECORD
