Metadata-Version: 2.1
Name: oftest
Version: 0.2.1
Summary: test framework for OpenFOAM
Home-page: https://github.com/HenningScheufler/oftest
Author: Henning Scheufler
Author-email: henning.scheufler@dlr.de
License: GPLv3
Project-URL: Documentation, https://oftest.readthedocs.io/
Project-URL: Changelog, https://oftest.readthedocs.io/en/latest/changelog.html
Project-URL: Issue Tracker, https://github.com/HenningScheufler/oftest/issues
Keywords: openfoam,cfd,pytest,testing
Platform: UNKNOWN
Classifier: Development Status :: 3 - Alpha
Classifier: Intended Audience :: Developers
Classifier: License :: OSI Approved :: GNU General Public License v3 or later (GPLv3+)
Classifier: Operating System :: Unix
Classifier: Operating System :: POSIX
Classifier: Operating System :: Microsoft :: Windows
Classifier: Programming Language :: Python
Classifier: Programming Language :: Python :: 3
Classifier: Programming Language :: Python :: 3 :: Only
Classifier: Programming Language :: Python :: 3.6
Classifier: Programming Language :: Python :: 3.7
Classifier: Programming Language :: Python :: 3.8
Classifier: Programming Language :: Python :: 3.9
Classifier: Programming Language :: Python :: Implementation :: CPython
Classifier: Programming Language :: Python :: Implementation :: PyPy
Classifier: Topic :: Utilities
Requires-Python: >=3.6
License-File: LICENSE
License-File: AUTHORS.rst
Requires-Dist: pandas (>=0.21.0)
Requires-Dist: pyfoam (>=0.6.8)
Requires-Dist: pytest (>=6.0.0)
Provides-Extra: dev
Requires-Dist: tox (>=3.0.0) ; extra == 'dev'
